{
"autoplayBgm":true,"autoplayBgs":false,"battleback1Name":"Cobblestones3","battleback2Name":"RockCave","bgm":{"name":"Dungeon1","pan":0,"pitch":100,"volume":90},"bgs":{"name":"","pan":0,"pitch":100,"volume":90},"disableDashing":false,"displayName":"Storage","encounterList":[{"regionSet":[],"troopId":12,"weight":5}],"encounterStep":30,"height":8,"note":"","parallaxLoopX":false,"parallaxLoopY":false,"parallaxName":"","parallaxShow":true,"parallaxSx":0,"parallaxSy":0,"scrollType":0,"specifyBattleback":true,"tilesetId":3,"width":15,
"data":[5916,5916,5916,5916,5916,5916,5916,5916,5916,5916,5916,5916,5916,5916,5896,6283,6282,6282,6282,6282,6282,6282,6282,6282,6282,6282,6282,6282,6282,5904,1631,3283,3281,3270,3268,3268,3268,3284,1631,1631,1631,1631,3282,3284,5904,1631,3280,1631,3264,3248,3248,3248,3250,3268,3284,1631,3282,3249,3272,5904,3268,3251,3268,3249,3248,3248,3248,3248,3248,3250,3268,3249,3248,3272,5904,3276,3276,3256,3248,3252,3276,3276,3276,3256,3248,3248,3248,3252,3286,5904,1631,1631,3288,3276,3286,1631,1631,1631,3288,3276,3276,3276,3286,1631,5904,5908,5908,5908,5908,5908,5908,5908,5908,5908,5908,5908,5908,5908,5908,5889,0,0,0,0,0,0,0,0,0,0,0,0,0,0,0,0,0,0,0,0,0,0,0,0,0,0,0,0,0,0,0,0,0,0,0,0,0,0,0,0,0,0,0,0,0,0,0,0,0,0,0,0,0,0,0,0,0,0,0,0,0,0,0,0,0,0,0,0,0,0,0,0,0,0,0,0,0,0,0,0,0,0,0,0,0,0,0,0,0,0,0,0,0,0,0,0,0,0,0,0,0,0,0,0,0,0,0,0,0,0,0,0,0,0,0,0,0,0,0,0,0,0,0,0,0,0,0,0,0,0,0,0,0,0,0,0,0,0,0,0,0,0,0,0,0,0,0,0,0,0,0,0,0,0,0,0,0,0,0,0,0,0,0,0,0,0,0,0,0,0,0,0,0,0,0,0,0,0,0,0,0,0,0,0,0,0,0,0,0,0,0,0,0,208,0,0,0,0,0,0,0,0,0,0,0,0,0,0,0,0,0,0,0,0,0,0,0,0,0,0,0,0,0,0,0,0,0,0,0,0,0,0,0,0,0,0,0,0,0,0,0,0,0,0,0,0,0,0,0,0,0,0,0,0,0,0,231,0,0,163,0,0,0,0,242,242,0,0,231,0,200,201,0,200,0,0,207,0,201,250,250,0,0,0,0,200,201,0,0,0,0,0,0,248,201,0,0,0,0,0,2,0,0,0,0,0,0,0,0,0,0,0,0,240,0,0,0,0,0,0,224,209,0,0,0,0,0,210,201,0,0,208,233,0,224,224,209,209,209,0,0,0,200,201,0,0,0,0,0,0,0,0,0,0,0,0,0,0,0,0,0,0,0,0,0,0,0,0,0,0,0,0,0,0,0,0,0,0,0,0,0,0,0,0,0,0,0,0,0,0,0,0,0,0,0,0,0,0,0,0,0,0,0,0,0,0,0,0,0,0,0,0,0,0,0,0,0,0,0,0,0,0,0,0,0,0,0,0,0,0,0,0,0,0,0,0,0,0,0,0,0,0,0,0,0,0,0,0,0,0,0,0,0,0,0,0,0,0,0,0,0,0,0,0,0,0,0,0,0,0,0,0,0,0,0,0,0,0,0,0,0,0,0,0,0,0,0,0,0,0,0,0,0,0,0,0,0,0,0,0,0,0,0,0,0,0,0,0,0,0,0,0,0,0,0,0,0,0,0,0,0,0,0,0,0,0,0,0,0,0,0,0,0,0,0,0,0,0,0,0,0,0,0,0,0,0,0,0,0,0,0,0,0,0,0,0,0,0,0,0,0,0,0,0,0,0,0,0,0,0,0,0,0,0,0,0,0,0,0,0,0,0,0,0,0,0,0,0,0,0,0,0,0,0,0,0,0,0,0,0],
"events":[
null,
{"id":1,"name":"EV001","note":"","pages":[{"conditions":{"actorId":1,"actorValid":false,"itemId":1,"itemValid":false,"selfSwitchCh":"A","selfSwitchValid":false,"switch1Id":1,"switch1Valid":false,"switch2Id":1,"switch2Valid":false,"variableId":1,"variableValid":false,"variableValue":0},"directionFix":false,"image":{"characterIndex":0,"characterName":"","direction":2,"pattern":0,"tileId":0},"list":[{"code":242,"indent":0,"parameters":[5]},{"code":201,"indent":0,"parameters":[0,2,22,16,2,0]},{"code":0,"indent":0,"parameters":[]}],"moveFrequency":3,"moveRoute":{"list":[{"code":0,"parameters":[]}],"repeat":true,"skippable":false,"wait":false},"moveSpeed":3,"moveType":0,"priorityType":0,"stepAnime":false,"through":false,"trigger":1,"walkAnime":true}],"x":0,"y":4},
null,
null,
{"id":4,"name":"EV004","note":"","pages":[{"conditions":{"actorId":1,"actorValid":false,"itemId":1,"itemValid":false,"selfSwitchCh":"A","selfSwitchValid":false,"switch1Id":1,"switch1Valid":false,"switch2Id":1,"switch2Valid":false,"variableId":1,"variableValid":false,"variableValue":0},"directionFix":false,"image":{"characterIndex":0,"characterName":"","direction":2,"pattern":0,"tileId":0},"list":[{"code":101,"indent":0,"parameters":["Rico",0,0,2]},{"code":401,"indent":0,"parameters":["Rico:"]},{"code":401,"indent":0,"parameters":["\"There's a lot of jar here.\""]},{"code":0,"indent":0,"parameters":[]}],"moveFrequency":3,"moveRoute":{"list":[{"code":0,"parameters":[]}],"repeat":true,"skippable":false,"wait":false},"moveSpeed":3,"moveType":0,"priorityType":1,"stepAnime":false,"through":false,"trigger":0,"walkAnime":true}],"x":1,"y":3},
{"id":5,"name":"EV005","note":"","pages":[{"conditions":{"actorId":1,"actorValid":false,"itemId":1,"itemValid":false,"selfSwitchCh":"A","selfSwitchValid":false,"switch1Id":1,"switch1Valid":false,"switch2Id":1,"switch2Valid":false,"variableId":1,"variableValid":false,"variableValue":0},"directionFix":false,"image":{"characterIndex":0,"characterName":"","direction":2,"pattern":0,"tileId":0},"list":[{"code":101,"indent":0,"parameters":["Rico",0,0,2]},{"code":401,"indent":0,"parameters":["Rico:"]},{"code":401,"indent":0,"parameters":["\"There's a lot of jar here.\""]},{"code":0,"indent":0,"parameters":[]}],"moveFrequency":3,"moveRoute":{"list":[{"code":0,"parameters":[]}],"repeat":true,"skippable":false,"wait":false},"moveSpeed":3,"moveType":0,"priorityType":1,"stepAnime":false,"through":false,"trigger":0,"walkAnime":true}],"x":1,"y":2},
{"id":6,"name":"EV006","note":"","pages":[{"conditions":{"actorId":1,"actorValid":false,"itemId":1,"itemValid":false,"selfSwitchCh":"A","selfSwitchValid":false,"switch1Id":1,"switch1Valid":false,"switch2Id":1,"switch2Valid":false,"variableId":1,"variableValid":false,"variableValue":0},"directionFix":false,"image":{"characterIndex":0,"characterName":"","direction":2,"pattern":0,"tileId":0},"list":[{"code":101,"indent":0,"parameters":["Rico",0,0,2]},{"code":401,"indent":0,"parameters":["Rico:"]},{"code":401,"indent":0,"parameters":["\"There's a lot of jar here.\""]},{"code":0,"indent":0,"parameters":[]}],"moveFrequency":3,"moveRoute":{"list":[{"code":0,"parameters":[]}],"repeat":true,"skippable":false,"wait":false},"moveSpeed":3,"moveType":0,"priorityType":1,"stepAnime":false,"through":false,"trigger":0,"walkAnime":true}],"x":9,"y":3},
{"id":7,"name":"EV007","note":"","pages":[{"conditions":{"actorId":1,"actorValid":false,"itemId":1,"itemValid":false,"selfSwitchCh":"A","selfSwitchValid":false,"switch1Id":1,"switch1Valid":false,"switch2Id":1,"switch2Valid":false,"variableId":1,"variableValid":false,"variableValue":0},"directionFix":false,"image":{"characterIndex":0,"characterName":"","direction":2,"pattern":0,"tileId":0},"list":[{"code":101,"indent":0,"parameters":["Rico",0,0,2]},{"code":401,"indent":0,"parameters":["Rico:"]},{"code":401,"indent":0,"parameters":["\"There's a lot of jar here.\""]},{"code":0,"indent":0,"parameters":[]}],"moveFrequency":3,"moveRoute":{"list":[{"code":0,"parameters":[]}],"repeat":true,"skippable":false,"wait":false},"moveSpeed":3,"moveType":0,"priorityType":1,"stepAnime":false,"through":false,"trigger":0,"walkAnime":true}],"x":8,"y":2},
{"id":8,"name":"EV008","note":"","pages":[{"conditions":{"actorId":1,"actorValid":false,"itemId":1,"itemValid":false,"selfSwitchCh":"A","selfSwitchValid":false,"switch1Id":1,"switch1Valid":false,"switch2Id":1,"switch2Valid":false,"variableId":1,"variableValid":false,"variableValue":0},"directionFix":false,"image":{"characterIndex":0,"characterName":"","direction":2,"pattern":0,"tileId":0},"list":[{"code":101,"indent":0,"parameters":["Rico",0,0,2]},{"code":401,"indent":0,"parameters":["Rico:"]},{"code":401,"indent":0,"parameters":["\"Apples.\""]},{"code":101,"indent":0,"parameters":["Emily",4,0,2]},{"code":401,"indent":0,"parameters":["Miho:"]},{"code":401,"indent":0,"parameters":["\"Don't eat Rico-sama, it's not ours.\""]},{"code":101,"indent":0,"parameters":["Rico",0,0,2]},{"code":401,"indent":0,"parameters":["Rico:"]},{"code":401,"indent":0,"parameters":["\"*munch*...*munch*..what?\""]},{"code":311,"indent":0,"parameters":[0,1,0,0,100,false]},{"code":101,"indent":0,"parameters":["",0,0,2]},{"code":401,"indent":0,"parameters":["Rico gain 100 HP "]},{"code":123,"indent":0,"parameters":["A",0]},{"code":0,"indent":0,"parameters":[]}],"moveFrequency":3,"moveRoute":{"list":[{"code":0,"parameters":[]}],"repeat":true,"skippable":false,"wait":false},"moveSpeed":3,"moveType":0,"priorityType":1,"stepAnime":false,"through":false,"trigger":0,"walkAnime":true},{"conditions":{"actorId":1,"actorValid":false,"itemId":1,"itemValid":false,"selfSwitchCh":"A","selfSwitchValid":true,"switch1Id":1,"switch1Valid":false,"switch2Id":1,"switch2Valid":false,"variableId":1,"variableValid":false,"variableValue":0},"directionFix":false,"image":{"characterIndex":0,"characterName":"","direction":2,"pattern":0,"tileId":0},"list":[{"code":101,"indent":0,"parameters":["Emily",5,0,2]},{"code":401,"indent":0,"parameters":["Miho:"]},{"code":401,"indent":0,"parameters":["\"Rico-sama!\""]},{"code":101,"indent":0,"parameters":["Rico",3,0,2]},{"code":401,"indent":0,"parameters":["Rico:"]},{"code":401,"indent":0,"parameters":["\"Okay..okay..\""]},{"code":0,"indent":0,"parameters":[]}],"moveFrequency":3,"moveRoute":{"list":[{"code":0,"parameters":[]}],"repeat":true,"skippable":false,"wait":false},"moveSpeed":3,"moveType":0,"priorityType":1,"stepAnime":false,"through":false,"trigger":0,"walkAnime":true},{"conditions":{"actorId":1,"actorValid":false,"itemId":1,"itemValid":false,"selfSwitchCh":"A","selfSwitchValid":false,"switch1Id":21,"switch1Valid":true,"switch2Id":1,"switch2Valid":false,"variableId":1,"variableValid":false,"variableValue":0},"directionFix":false,"image":{"characterIndex":0,"characterName":"","direction":2,"pattern":0,"tileId":0},"list":[{"code":101,"indent":0,"parameters":["Rico",0,0,2]},{"code":401,"indent":0,"parameters":["Rico:"]},{"code":401,"indent":0,"parameters":["\"Apples.\""]},{"code":0,"indent":0,"parameters":[]}],"moveFrequency":3,"moveRoute":{"list":[{"code":0,"parameters":[]}],"repeat":true,"skippable":false,"wait":false},"moveSpeed":3,"moveType":0,"priorityType":1,"stepAnime":false,"through":false,"trigger":0,"walkAnime":true}],"x":2,"y":6},
{"id":9,"name":"EV009","note":"","pages":[{"conditions":{"actorId":1,"actorValid":false,"itemId":1,"itemValid":false,"selfSwitchCh":"A","selfSwitchValid":false,"switch1Id":1,"switch1Valid":false,"switch2Id":1,"switch2Valid":false,"variableId":1,"variableValid":false,"variableValue":0},"directionFix":false,"image":{"characterIndex":0,"characterName":"","direction":2,"pattern":0,"tileId":0},"list":[{"code":101,"indent":0,"parameters":["Rico",0,0,2]},{"code":401,"indent":0,"parameters":["Rico:"]},{"code":401,"indent":0,"parameters":["\"Carrots.\""]},{"code":101,"indent":0,"parameters":["Emily",7,0,2]},{"code":401,"indent":0,"parameters":["Miho:"]},{"code":401,"indent":0,"parameters":["\"Don't try to eat it ,Rico-sama.\""]},{"code":101,"indent":0,"parameters":["Rico",0,0,2]},{"code":401,"indent":0,"parameters":["Rico:"]},{"code":401,"indent":0,"parameters":["\"I don't like carrots.\""]},{"code":101,"indent":0,"parameters":["Emily",7,0,2]},{"code":401,"indent":0,"parameters":["Miho:"]},{"code":401,"indent":0,"parameters":["\"Vegetables are good for you ,Rico-sama.\""]},{"code":101,"indent":0,"parameters":["Rico",4,0,2]},{"code":401,"indent":0,"parameters":["Rico:"]},{"code":401,"indent":0,"parameters":["\"So i can eat it then?\""]},{"code":101,"indent":0,"parameters":["Emily",5,0,2]},{"code":401,"indent":0,"parameters":["Miho:"]},{"code":401,"indent":0,"parameters":["\"No!\""]},{"code":101,"indent":0,"parameters":["Emily",5,0,2]},{"code":401,"indent":0,"parameters":["Miho:"]},{"code":401,"indent":0,"parameters":["\"It's not ours.\""]},{"code":101,"indent":0,"parameters":["Rico",3,0,2]},{"code":401,"indent":0,"parameters":["Rico:"]},{"code":401,"indent":0,"parameters":["\"Haaa...you need to make up your mind,"]},{"code":401,"indent":0,"parameters":["Miho.\""]},{"code":101,"indent":0,"parameters":["Emily",7,0,2]},{"code":401,"indent":0,"parameters":["Miho:"]},{"code":401,"indent":0,"parameters":["\"Rico-sama.\""]},{"code":123,"indent":0,"parameters":["A",0]},{"code":0,"indent":0,"parameters":[]}],"moveFrequency":3,"moveRoute":{"list":[{"code":0,"parameters":[]}],"repeat":true,"skippable":false,"wait":false},"moveSpeed":3,"moveType":0,"priorityType":1,"stepAnime":false,"through":false,"trigger":0,"walkAnime":true},{"conditions":{"actorId":1,"actorValid":false,"itemId":1,"itemValid":false,"selfSwitchCh":"A","selfSwitchValid":true,"switch1Id":1,"switch1Valid":false,"switch2Id":1,"switch2Valid":false,"variableId":1,"variableValid":false,"variableValue":0},"directionFix":false,"image":{"characterIndex":0,"characterName":"","direction":2,"pattern":0,"tileId":0},"list":[{"code":101,"indent":0,"parameters":["Rico",0,0,2]},{"code":401,"indent":0,"parameters":["Rico:"]},{"code":401,"indent":0,"parameters":["\"I still don't like carrots.\""]},{"code":0,"indent":0,"parameters":[]}],"moveFrequency":3,"moveRoute":{"list":[{"code":0,"parameters":[]}],"repeat":true,"skippable":false,"wait":false},"moveSpeed":3,"moveType":0,"priorityType":1,"stepAnime":false,"through":false,"trigger":0,"walkAnime":true},{"conditions":{"actorId":1,"actorValid":false,"itemId":1,"itemValid":false,"selfSwitchCh":"A","selfSwitchValid":false,"switch1Id":21,"switch1Valid":true,"switch2Id":1,"switch2Valid":false,"variableId":1,"variableValid":false,"variableValue":0},"directionFix":false,"image":{"characterIndex":0,"characterName":"","direction":2,"pattern":0,"tileId":0},"list":[{"code":101,"indent":0,"parameters":["Rico",0,0,2]},{"code":401,"indent":0,"parameters":["Rico:"]},{"code":401,"indent":0,"parameters":["\"Carrots.\""]},{"code":0,"indent":0,"parameters":[]}],"moveFrequency":3,"moveRoute":{"list":[{"code":0,"parameters":[]}],"repeat":true,"skippable":false,"wait":false},"moveSpeed":3,"moveType":0,"priorityType":1,"stepAnime":false,"through":false,"trigger":0,"walkAnime":true}],"x":13,"y":4},
{"id":10,"name":"EV010","note":"","pages":[{"conditions":{"actorId":1,"actorValid":false,"itemId":1,"itemValid":false,"selfSwitchCh":"A","selfSwitchValid":false,"switch1Id":1,"switch1Valid":false,"switch2Id":1,"switch2Valid":false,"variableId":1,"variableValid":false,"variableValue":0},"directionFix":false,"image":{"characterIndex":0,"characterName":"","direction":2,"pattern":0,"tileId":0},"list":[{"code":101,"indent":0,"parameters":["Rico",0,0,2]},{"code":401,"indent":0,"parameters":["Rico:"]},{"code":401,"indent":0,"parameters":["\"There's nothing in it.\""]},{"code":0,"indent":0,"parameters":[]}],"moveFrequency":3,"moveRoute":{"list":[{"code":0,"parameters":[]}],"repeat":true,"skippable":false,"wait":false},"moveSpeed":3,"moveType":0,"priorityType":1,"stepAnime":false,"through":false,"trigger":0,"walkAnime":true}],"x":3,"y":2},
{"id":11,"name":"EV011","note":"","pages":[{"conditions":{"actorId":1,"actorValid":false,"itemId":1,"itemValid":false,"selfSwitchCh":"A","selfSwitchValid":false,"switch1Id":1,"switch1Valid":false,"switch2Id":1,"switch2Valid":false,"variableId":1,"variableValid":false,"variableValue":0},"directionFix":false,"image":{"characterIndex":0,"characterName":"","direction":2,"pattern":0,"tileId":0},"list":[{"code":101,"indent":0,"parameters":["Rico",0,0,2]},{"code":401,"indent":0,"parameters":["Rico:"]},{"code":401,"indent":0,"parameters":["\"There's nothing in it.\""]},{"code":0,"indent":0,"parameters":[]}],"moveFrequency":3,"moveRoute":{"list":[{"code":0,"parameters":[]}],"repeat":true,"skippable":false,"wait":false},"moveSpeed":3,"moveType":0,"priorityType":1,"stepAnime":false,"through":false,"trigger":0,"walkAnime":true}],"x":1,"y":6},
{"id":12,"name":"EV012","note":"","pages":[{"conditions":{"actorId":1,"actorValid":false,"itemId":1,"itemValid":false,"selfSwitchCh":"A","selfSwitchValid":false,"switch1Id":1,"switch1Valid":false,"switch2Id":1,"switch2Valid":false,"variableId":1,"variableValid":false,"variableValue":0},"directionFix":false,"image":{"characterIndex":0,"characterName":"","direction":2,"pattern":0,"tileId":0},"list":[{"code":101,"indent":0,"parameters":["Rico",0,0,2]},{"code":401,"indent":0,"parameters":["Rico:"]},{"code":401,"indent":0,"parameters":["\"A barrel.\""]},{"code":0,"indent":0,"parameters":[]}],"moveFrequency":3,"moveRoute":{"list":[{"code":0,"parameters":[]}],"repeat":true,"skippable":false,"wait":false},"moveSpeed":3,"moveType":0,"priorityType":1,"stepAnime":false,"through":false,"trigger":0,"walkAnime":true}],"x":6,"y":5},
{"id":13,"name":"EV013","note":"","pages":[{"conditions":{"actorId":1,"actorValid":false,"itemId":1,"itemValid":false,"selfSwitchCh":"A","selfSwitchValid":false,"switch1Id":1,"switch1Valid":false,"switch2Id":1,"switch2Valid":false,"variableId":1,"variableValid":false,"variableValue":0},"directionFix":false,"image":{"characterIndex":0,"characterName":"","direction":2,"pattern":0,"tileId":0},"list":[{"code":101,"indent":0,"parameters":["Rico",0,0,2]},{"code":401,"indent":0,"parameters":["Rico:"]},{"code":401,"indent":0,"parameters":["\"There something in the barrel.\""]},{"code":125,"indent":0,"parameters":[0,0,100]},{"code":101,"indent":0,"parameters":["",0,0,2]},{"code":401,"indent":0,"parameters":["Got 100G."]},{"code":101,"indent":0,"parameters":["Emily",2,0,2]},{"code":401,"indent":0,"parameters":["Miho:"]},{"code":401,"indent":0,"parameters":["\"No, Rico-sama that's stealing. Put it "]},{"code":401,"indent":0,"parameters":["back.\""]},{"code":101,"indent":0,"parameters":["",0,0,2]},{"code":401,"indent":0,"parameters":["Lose 100G."]},{"code":125,"indent":0,"parameters":[1,0,100]},{"code":101,"indent":0,"parameters":["Rico",3,0,2]},{"code":401,"indent":0,"parameters":["Rico:"]},{"code":401,"indent":0,"parameters":["\"Okay.\""]},{"code":123,"indent":0,"parameters":["A",0]},{"code":0,"indent":0,"parameters":[]}],"moveFrequency":3,"moveRoute":{"list":[{"code":0,"parameters":[]}],"repeat":true,"skippable":false,"wait":false},"moveSpeed":3,"moveType":0,"priorityType":1,"stepAnime":false,"through":false,"trigger":0,"walkAnime":true},{"conditions":{"actorId":1,"actorValid":false,"itemId":1,"itemValid":false,"selfSwitchCh":"A","selfSwitchValid":true,"switch1Id":1,"switch1Valid":false,"switch2Id":1,"switch2Valid":false,"variableId":1,"variableValid":false,"variableValue":0},"directionFix":false,"image":{"characterIndex":0,"characterName":"","direction":2,"pattern":0,"tileId":0},"list":[{"code":101,"indent":0,"parameters":["Emily",7,0,2]},{"code":401,"indent":0,"parameters":["Miho:"]},{"code":401,"indent":0,"parameters":["\"That's not ours, Rico-sama.\""]},{"code":0,"indent":0,"parameters":[]}],"moveFrequency":3,"moveRoute":{"list":[{"code":0,"parameters":[]}],"repeat":true,"skippable":false,"wait":false},"moveSpeed":3,"moveType":0,"priorityType":1,"stepAnime":false,"through":false,"trigger":0,"walkAnime":true},{"conditions":{"actorId":1,"actorValid":false,"itemId":1,"itemValid":false,"selfSwitchCh":"A","selfSwitchValid":false,"switch1Id":21,"switch1Valid":true,"switch2Id":1,"switch2Valid":false,"variableId":1,"variableValid":false,"variableValue":0},"directionFix":false,"image":{"characterIndex":0,"characterName":"","direction":2,"pattern":0,"tileId":0},"list":[{"code":101,"indent":0,"parameters":["Rico",0,0,2]},{"code":401,"indent":0,"parameters":["Rico:"]},{"code":401,"indent":0,"parameters":["\"There something in the barrel.\""]},{"code":0,"indent":0,"parameters":[]}],"moveFrequency":3,"moveRoute":{"list":[{"code":0,"parameters":[]}],"repeat":true,"skippable":false,"wait":false},"moveSpeed":3,"moveType":0,"priorityType":1,"stepAnime":false,"through":false,"trigger":0,"walkAnime":true}],"x":12,"y":5},
{"id":14,"name":"EV014","note":"","pages":[{"conditions":{"actorId":1,"actorValid":false,"itemId":1,"itemValid":false,"selfSwitchCh":"A","selfSwitchValid":false,"switch1Id":1,"switch1Valid":false,"switch2Id":1,"switch2Valid":false,"variableId":1,"variableValid":false,"variableValue":0},"directionFix":false,"image":{"characterIndex":0,"characterName":"","direction":2,"pattern":0,"tileId":0},"list":[{"code":101,"indent":0,"parameters":["Rico",0,0,2]},{"code":401,"indent":0,"parameters":["Rico:"]},{"code":401,"indent":0,"parameters":["\"A barrel.\""]},{"code":0,"indent":0,"parameters":[]}],"moveFrequency":3,"moveRoute":{"list":[{"code":0,"parameters":[]}],"repeat":true,"skippable":false,"wait":false},"moveSpeed":3,"moveType":0,"priorityType":1,"stepAnime":false,"through":false,"trigger":0,"walkAnime":true}],"x":7,"y":6},
{"id":15,"name":"EV015","note":"","pages":[{"conditions":{"actorId":1,"actorValid":false,"itemId":1,"itemValid":false,"selfSwitchCh":"A","selfSwitchValid":false,"switch1Id":1,"switch1Valid":false,"switch2Id":1,"switch2Valid":false,"variableId":1,"variableValid":false,"variableValue":0},"directionFix":false,"image":{"characterIndex":0,"characterName":"","direction":2,"pattern":0,"tileId":0},"list":[{"code":101,"indent":0,"parameters":["Rico",0,0,2]},{"code":401,"indent":0,"parameters":["Rico:"]},{"code":401,"indent":0,"parameters":["\"A barrel.\""]},{"code":0,"indent":0,"parameters":[]}],"moveFrequency":3,"moveRoute":{"list":[{"code":0,"parameters":[]}],"repeat":true,"skippable":false,"wait":false},"moveSpeed":3,"moveType":0,"priorityType":1,"stepAnime":false,"through":false,"trigger":0,"walkAnime":true}],"x":8,"y":6},
{"id":16,"name":"EV016","note":"","pages":[{"conditions":{"actorId":1,"actorValid":false,"itemId":1,"itemValid":false,"selfSwitchCh":"A","selfSwitchValid":false,"switch1Id":1,"switch1Valid":false,"switch2Id":1,"switch2Valid":false,"variableId":1,"variableValid":false,"variableValue":0},"directionFix":false,"image":{"tileId":202,"characterName":"","characterIndex":0,"direction":2,"pattern":0},"list":[{"code":101,"indent":0,"parameters":["Rico",0,0,2]},{"code":401,"indent":0,"parameters":["Rico:"]},{"code":401,"indent":0,"parameters":["\"A broken jar. I can patch it up.\""]},{"code":102,"indent":0,"parameters":[["Patch it up","No"],1,0,2,0]},{"code":402,"indent":0,"parameters":[0,"Patch it up"]},{"code":212,"indent":1,"parameters":[0,42,true]},{"code":123,"indent":1,"parameters":["A",0]},{"code":0,"indent":1,"parameters":[]},{"code":402,"indent":0,"parameters":[1,"No"]},{"code":0,"indent":1,"parameters":[]},{"code":404,"indent":0,"parameters":[]},{"code":0,"indent":0,"parameters":[]}],"moveFrequency":3,"moveRoute":{"list":[{"code":0,"parameters":[]}],"repeat":true,"skippable":false,"wait":false},"moveSpeed":3,"moveType":0,"priorityType":1,"stepAnime":false,"through":false,"trigger":0,"walkAnime":true},{"conditions":{"actorId":1,"actorValid":false,"itemId":1,"itemValid":false,"selfSwitchCh":"A","selfSwitchValid":true,"switch1Id":1,"switch1Valid":false,"switch2Id":1,"switch2Valid":false,"variableId":1,"variableValid":false,"variableValue":0},"directionFix":false,"image":{"tileId":200,"characterName":"","characterIndex":0,"direction":2,"pattern":0},"list":[{"code":101,"indent":0,"parameters":["Rico",1,0,2]},{"code":401,"indent":0,"parameters":["Rico:"]},{"code":401,"indent":0,"parameters":["\"There, good as new.\""]},{"code":111,"indent":0,"parameters":[0,13,0]},{"code":101,"indent":1,"parameters":["Emily",0,0,2]},{"code":401,"indent":1,"parameters":["Miho:"]},{"code":401,"indent":1,"parameters":["\"Good job ,Rico-sama.\""]},{"code":101,"indent":1,"parameters":["Rico",4,0,2]},{"code":401,"indent":1,"parameters":["Rico:"]},{"code":401,"indent":1,"parameters":["\"Now, let's ask the villager to pay us for"]},{"code":401,"indent":1,"parameters":["fixing their jar.\""]},{"code":101,"indent":1,"parameters":["Emily",4,0,2]},{"code":401,"indent":1,"parameters":["Miho:"]},{"code":401,"indent":1,"parameters":["\"Rico-sama!\""]},{"code":101,"indent":1,"parameters":["Rico",3,0,2]},{"code":401,"indent":1,"parameters":["Rico:"]},{"code":401,"indent":1,"parameters":["\"Okay, Miho.\""]},{"code":0,"indent":1,"parameters":[]},{"code":412,"indent":0,"parameters":[]},{"code":123,"indent":0,"parameters":["B",0]},{"code":0,"indent":0,"parameters":[]}],"moveFrequency":3,"moveRoute":{"list":[{"code":0,"parameters":[]}],"repeat":true,"skippable":false,"wait":false},"moveSpeed":3,"moveType":0,"priorityType":1,"stepAnime":false,"through":false,"trigger":3,"walkAnime":true},{"conditions":{"actorId":1,"actorValid":false,"itemId":1,"itemValid":false,"selfSwitchCh":"B","selfSwitchValid":true,"switch1Id":1,"switch1Valid":false,"switch2Id":1,"switch2Valid":false,"variableId":1,"variableValid":false,"variableValue":0},"directionFix":false,"image":{"tileId":200,"characterName":"","characterIndex":0,"direction":2,"pattern":0},"list":[{"code":101,"indent":0,"parameters":["Rico",1,0,2]},{"code":401,"indent":0,"parameters":["Rico:"]},{"code":401,"indent":0,"parameters":["\"I really make it better.\""]},{"code":0,"indent":0,"parameters":[]}],"moveFrequency":3,"moveRoute":{"list":[{"code":0,"parameters":[]}],"repeat":true,"skippable":false,"wait":false},"moveSpeed":3,"moveType":0,"priorityType":1,"stepAnime":false,"through":false,"trigger":0,"walkAnime":true}],"x":11,"y":6}
]
}